verilog/rtl/stoplight_example/counter.sv
module counter (
    input logic clk, nrst, //clock and negative-edge reset
    //other signals here
    input logic clear, enable,
    output logic max_count
);
    //module code here
    logic [7:0] count_d, count_q;

    always_ff @(posedge clk, negedge nrst) begin: count_register
        if (!nrst) begin
            count_q <= '0;
        end else begin
            count_q <= count_d;
        end
    end

    always_comb begin: next_count_logic
        count_d = count_q;
        if (clear || max_count) begin
            count_d = '0;
        end else if (enable) begin
            count_d = count_q + 1;
        end
    end

    always_comb begin: output_logic
        max_count = 0;
        if (count_q == 8'd10) begin
            max_count = 1;
        end
    end
    
endmodule

verilog/dv/stoplight_example/counter_tb.sv
// $Id: $
// File name:   src1_tb.sv
// Created:     01/19/2026
// Author:      Alex Weyer
// Description: Template test bench

`timescale 1ns / 10ps

module counter_tb();

    // Define local parameters used by the test bench
    localparam  CLK_PERIOD = 10;
    
    // Declare DUT portmap signals
    logic clk;
    logic nrst;
    // etc...
    logic clear, enable, max_count;
    
    // Declare test bench signals
    integer tb_test_num;
    integer tb_passed;
    string tb_test_case;
    
    // Task for standard DUT reset procedure
    task reset_dut;
    begin
        // Activate the reset
        nrst = 1'b0;
        @(posedge clk);
        @(posedge clk);
        @(negedge clk);
        // deactivate reset
        nrst = 1'b1;
        @(negedge clk);
        @(negedge clk);
    end
    endtask

    // Add more tasks as needed


    // Clock generation block
    always
    begin
        #(CLK_PERIOD/2.0); clk ++;
    end

    // Signal dump
    initial begin
        $dumpfile ("support/waves/stoplight_example/counter.vcd");
        $dumpvars;
    end
    
    // DUT Port map
    counter DUT(.*); // .* is a shortcut to automatically connect all ports if names match
    
    // Test bench main process
    initial
    begin
        // Initialize all of the test inputs here
        clk = 0;
        nrst = 1;
        // etc...
        enable = 1;
        clear = 0;

        // ************************************************************************
        // Test Case 1: Power-on Reset of the DUT
        // ************************************************************************
        tb_test_case = "Power on Reset";

        reset_dut();

        // ************************************************************************
        // Test Case 2: Continuous counting
        // ************************************************************************    
        tb_test_case = "Continuous counting";
        repeat (5) @(negedge clk);
        clear = 1;
        tb_test_case = "clear";
        repeat (3) @(negedge clk);
        clear = 0;
        tb_test_case = "Continuous counting";
        repeat (5) @(negedge clk);
        enable = 0;
        tb_test_case = "disabled";
        repeat (3) @(negedge clk);
        enable = 1;
        tb_test_case = "wrap around";
        repeat(10) @(negedge clk);

        $display("\nTest cases passed: %1d/%1d\n", tb_passed, tb_test_num);
        $finish;

    end

endmodule

support/waves/stoplight_example/counter.vcd
$date
	Thu Jan 22 13:22:27 2026
$end
$version
	Icarus Verilog
$end
$timescale
	10ps
$end
$scope module counter_tb $end
$var wire 1 ! max_count $end
$var reg 1 " clear $end
$var reg 1 # clk $end
$var reg 1 $ enable $end
$var reg 1 % nrst $end
$var integer 32 & tb_passed [31:0] $end
$var integer 32 ' tb_test_num [31:0] $end
$scope module DUT $end
$var wire 1 " clear $end
$var wire 1 # clk $end
$var wire 1 $ enable $end
$var wire 1 % nrst $end
$var reg 8 ( count_d [7:0] $end
$var reg 8 ) count_q [7:0] $end
$var reg 1 ! max_count $end
$scope begin count_register $end
$upscope $end
$scope begin next_count_logic $end
$upscope $end
$scope begin output_logic $end
$upscope $end
$upscope $end
$scope task reset_dut $end
$upscope $end
$upscope $end
$enddefinitions $end
#0
$dumpvars
b0 )
b1 (
bx '
bx &
0%
1$
0#
0"
0!
$end
#500
1#
#1000
0#
#1500
1#
#2000
1%
0#
#2500
b10 (
b1 )
1#
#3000
0#
#3500
b11 (
b10 )
1#
#4000
0#
#4500
b100 (
b11 )
1#
#5000
0#
#5500
b101 (
b100 )
1#
#6000
0#
#6500
b110 (
b101 )
1#
#7000
0#
#7500
b111 (
b110 )
1#
#8000
0#
#8500
b1000 (
b111 )
1#
#9000
b0 (
1"
0#
#9500
b0 )
1#
#10000
0#
#10500
1#
#11000
0#
#11500
1#
#12000
b1 (
0"
0#
#12500
b10 (
b1 )
1#
#13000
0#
#13500
b11 (
b10 )
1#
#14000
0#
#14500
b100 (
b11 )
1#
#15000
0#
#15500
b101 (
b100 )
1#
#16000
0#
#16500
b110 (
b101 )
1#
#17000
b101 (
0$
0#
#17500
1#
#18000
0#
#18500
1#
#19000
0#
#19500
1#
#20000
b110 (
1$
0#
#20500
b111 (
b110 )
1#
#21000
0#
#21500
b1000 (
b111 )
1#
#22000
0#
#22500
b1001 (
b1000 )
1#
#23000
0#
#23500
b1010 (
b1001 )
1#
#24000
0#
#24500
1!
b0 (
b1010 )
1#
#25000
0#
#25500
b1 (
0!
b0 )
1#
#26000
0#
#26500
b10 (
b1 )
1#
#27000
0#
#27500
b11 (
b10 )
1#
#28000
0#
#28500
b100 (
b11 )
1#
#29000
0#
#29500
b101 (
b100 )
1#
